{"title":"멜론티켓 ─ 판매중","url":"https://ticket.melon.com/place/ajax/list_album.htm","favicon":"https://ticket.melon.com/place/ajax/favicon.ico","elements":[{"title":"치유의 기술 / Technique of Healing－부산","contents":"<td>\n                            <div class=\"show_infor\">\n                                <div class=\"thumb_90x125  img\">\n                                    <a href=\"#\">\n                                        <img onerror=\"noImage(this, 90, 125)\" src=\"https://cdnticket.melon.co.kr/resource/image/upload/product/2022/03/2022030715241512eef925-8c62-493e-8b87-6087b341f7cd.jpg/melon/resize/90x125/strip/true\" alt=\"\">\n                                        <span class=\"frame\"></span>\n                                    </a>\n                                </div>\n                                <p class=\"infor_text\">\n                                    <span class=\"ico_wrap\">\n                                        <span class=\"ico_list ico_list4\"> 판매중</span></span>\n                                    <span class=\"show_title\"><a href=\"/performance/index.htm?prodId=206655\">치유의 기술 / Technique of Healing－부산</a></span>\n                                </p>\n                            </div>\n                        </td>\n                        <td class=\"show_date\"><!-- @@@ 2016.02.01 class명 추가 -->\n                            2022.03.26 - 2023.05.07</td>\n                        <td class=\"show_loc\">뮤지엄 원 </td><!-- @@@ 2016.02.01 class명 추가 -->","link":"https://ticket.melon.com/performance/index.htm?prodId=206655","retrieved":1675595436890,"image":"https://cdnticket.melon.co.kr/resource/image/upload/product/2022/03/2022030715241512eef925-8c62-493e-8b87-6087b341f7cd.jpg/melon/resize/90x125/strip/true"},{"title":"프랑코 폰타나：컬러 인 라이프","contents":"<td>\n                            <div class=\"show_infor\">\n                                <div class=\"thumb_90x125  img\">\n                                    <a href=\"#\">\n                                        <img onerror=\"noImage(this, 90, 125)\" src=\"https://cdnticket.melon.co.kr/resource/image/upload/product/2022/09/2022092911383419866293-4561-4a1c-919b-adc94918ff8d.jpg/melon/resize/90x125/strip/true\" alt=\"\">\n                                        <span class=\"frame\"></span>\n                                    </a>\n                                </div>\n                                <p class=\"infor_text\">\n                                    <span class=\"ico_wrap\">\n                                        <span class=\"ico_list ico_list4\"> 판매중</span></span>\n                                    <span class=\"show_title\"><a href=\"/performance/index.htm?prodId=207379\">프랑코&nbsp;폰타나：컬러 인 라이프</a></span>\n                                </p>\n                            </div>\n                        </td>\n                        <td class=\"show_date\"><!-- @@@ 2016.02.01 class명 추가 -->\n                            2022.09.30 - 2023.03.01</td>\n                        <td class=\"show_loc\">마이아트뮤지엄 </td><!-- @@@ 2016.02.01 class명 추가 -->","link":"https://ticket.melon.com/performance/index.htm?prodId=207379","retrieved":1675595436892,"image":"https://cdnticket.melon.co.kr/resource/image/upload/product/2022/09/2022092911383419866293-4561-4a1c-919b-adc94918ff8d.jpg/melon/resize/90x125/strip/true"},{"title":"하리보 골드베렌 100주년 생일 기념전","contents":"<td>\n                            <div class=\"show_infor\">\n                                <div class=\"thumb_90x125  img\">\n                                    <a href=\"#\">\n                                        <img onerror=\"noImage(this, 90, 125)\" src=\"https://cdnticket.melon.co.kr/resource/image/upload/product/2022/10/202210121324282ba41fd7-0b2a-41e1-9f66-d12674c1bbf8.jpg/melon/resize/90x125/strip/true\" alt=\"\">\n                                        <span class=\"frame\"></span>\n                                    </a>\n                                </div>\n                                <p class=\"infor_text\">\n                                    <span class=\"ico_wrap\">\n                                        <span class=\"ico_list ico_list4\"> 판매중</span></span>\n                                    <span class=\"show_title\"><a href=\"/performance/index.htm?prodId=207416\">하리보 골드베렌 100주년 생일 기념전</a></span>\n                                </p>\n                            </div>\n                        </td>\n                        <td class=\"show_date\"><!-- @@@ 2016.02.01 class명 추가 -->\n                            2022.10.13 - 2023.03.12</td>\n                        <td class=\"show_loc\">안녕 인사동 B1 인사센트럴뮤지엄 </td><!-- @@@ 2016.02.01 class명 추가 -->","link":"https://ticket.melon.com/performance/index.htm?prodId=207416","retrieved":1675595436894,"image":"https://cdnticket.melon.co.kr/resource/image/upload/product/2022/10/202210121324282ba41fd7-0b2a-41e1-9f66-d12674c1bbf8.jpg/melon/resize/90x125/strip/true"},{"title":"뮤지컬 〈웨스트 사이드 스토리〉","contents":"<td>\n                            <div class=\"show_infor\">\n                                <div class=\"thumb_90x125  img\">\n                                    <a href=\"#\">\n                                        <img onerror=\"noImage(this, 90, 125)\" src=\"https://cdnticket.melon.co.kr/resource/image/upload/product/2022/09/202209071858267b4b3416-0656-4711-b7c2-956ff6449d64.jpg/melon/resize/90x125/strip/true\" alt=\"\">\n                                        <span class=\"frame\"></span>\n                                    </a>\n                                </div>\n                                <p class=\"infor_text\">\n                                    <span class=\"ico_wrap\">\n                                        <span class=\"ico_list ico_list1\">1열보유</span><span class=\"ico_list ico_list4\"> 판매중</span></span>\n                                    <span class=\"show_title\"><a href=\"/performance/index.htm?prodId=207296\">뮤지컬 〈웨스트 사이드 스토리〉</a></span>\n                                </p>\n                            </div>\n                        </td>\n                        <td class=\"show_date\"><!-- @@@ 2016.02.01 class명 추가 -->\n                            2022.11.17 - 2023.02.26</td>\n                        <td class=\"show_loc\">충무아트센터 대극장</td><!-- @@@ 2016.02.01 class명 추가 -->","link":"https://ticket.melon.com/performance/index.htm?prodId=207296","retrieved":1675595436910,"image":"https://cdnticket.melon.co.kr/resource/image/upload/product/2022/09/202209071858267b4b3416-0656-4711-b7c2-956ff6449d64.jpg/melon/resize/90x125/strip/true"},{"title":"헬가스텐첼 사진전","contents":"<td>\n                            <div class=\"show_infor\">\n                                <div class=\"thumb_90x125  img\">\n                                    <a href=\"#\">\n                                        <img onerror=\"noImage(this, 90, 125)\" src=\"https://cdnticket.melon.co.kr/resource/image/upload/product/2022/11/202211171608490eba859d-1b55-4c4f-99f6-241cadaaec0c.jpg/melon/resize/90x125/strip/true\" alt=\"\">\n                                        <span class=\"frame\"></span>\n                                    </a>\n                                </div>\n                                <p class=\"infor_text\">\n                                    <span class=\"ico_wrap\">\n                                        <span class=\"ico_list ico_list4\"> 판매중</span></span>\n                                    <span class=\"show_title\"><a href=\"/performance/index.htm?prodId=207583\">헬가스텐첼 사진전</a></span>\n                                </p>\n                            </div>\n                        </td>\n                        <td class=\"show_date\"><!-- @@@ 2016.02.01 class명 추가 -->\n                            2022.11.18 - 2023.03.01</td>\n                        <td class=\"show_loc\">롯데컬쳐스퀘어 CxC Art Museum </td><!-- @@@ 2016.02.01 class명 추가 -->","link":"https://ticket.melon.com/performance/index.htm?prodId=207583","retrieved":1675595436912,"image":"https://cdnticket.melon.co.kr/resource/image/upload/product/2022/11/202211171608490eba859d-1b55-4c4f-99f6-241cadaaec0c.jpg/melon/resize/90x125/strip/true"},{"title":"뮤지컬 〈이프덴〉","contents":"<td>\n                            <div class=\"show_infor\">\n                                <div class=\"thumb_90x125  img\">\n                                    <a href=\"#\">\n                                        <img onerror=\"noImage(this, 90, 125)\" src=\"https://cdnticket.melon.co.kr/resource/image/upload/product/2022/10/2022101210464406c2f97c-f12d-4632-8c75-7b84502afa7b.jpg/melon/resize/90x125/strip/true\" alt=\"\">\n                                        <span class=\"frame\"></span>\n                                    </a>\n                                </div>\n                                <p class=\"infor_text\">\n                                    <span class=\"ico_wrap\">\n                                        <span class=\"ico_list ico_list1\">1열보유</span><span class=\"ico_list ico_list4\"> 판매중</span></span>\n                                    <span class=\"show_title\"><a href=\"/performance/index.htm?prodId=207399\">뮤지컬 〈이프덴〉</a></span>\n                                </p>\n                            </div>\n                        </td>\n                        <td class=\"show_date\"><!-- @@@ 2016.02.01 class명 추가 -->\n                            2022.12.08 - 2023.02.26</td>\n                        <td class=\"show_loc\">홍익대학교 대학로 아트센터 대극장</td><!-- @@@ 2016.02.01 class명 추가 -->","link":"https://ticket.melon.com/performance/index.htm?prodId=207399","retrieved":1675595436917,"image":"https://cdnticket.melon.co.kr/resource/image/upload/product/2022/10/2022101210464406c2f97c-f12d-4632-8c75-7b84502afa7b.jpg/melon/resize/90x125/strip/true"},{"title":"DRIFT：In Sync with the Earth","contents":"<td>\n                            <div class=\"show_infor\">\n                                <div class=\"thumb_90x125  img\">\n                                    <a href=\"#\">\n                                        <img onerror=\"noImage(this, 90, 125)\" src=\"https://cdnticket.melon.co.kr/resource/image/upload/product/2022/12/202212061105295f572422-94ee-49c0-b916-142eb8aefbbb.jpg/melon/resize/90x125/strip/true\" alt=\"\">\n                                        <span class=\"frame\"></span>\n                                    </a>\n                                </div>\n                                <p class=\"infor_text\">\n                                    <span class=\"ico_wrap\">\n                                        <span class=\"ico_list ico_list4\"> 판매중</span></span>\n                                    <span class=\"show_title\"><a href=\"/performance/index.htm?prodId=207665\">DRIFT：In Sync with the Earth</a></span>\n                                </p>\n                            </div>\n                        </td>\n                        <td class=\"show_date\"><!-- @@@ 2016.02.01 class명 추가 -->\n                            2022.12.08 - 2023.04.16</td>\n                        <td class=\"show_loc\">현대카드 스토리지 </td><!-- @@@ 2016.02.01 class명 추가 -->","link":"https://ticket.melon.com/performance/index.htm?prodId=207665","retrieved":1675595436921,"image":"https://cdnticket.melon.co.kr/resource/image/upload/product/2022/12/202212061105295f572422-94ee-49c0-b916-142eb8aefbbb.jpg/melon/resize/90x125/strip/true"},{"title":"WATSON，THE MAESTRO－알버트 왓슨 사진전","contents":"<td>\n                            <div class=\"show_infor\">\n                                <div class=\"thumb_90x125  img\">\n                                    <a href=\"#\">\n                                        <img onerror=\"noImage(this, 90, 125)\" src=\"https://cdnticket.melon.co.kr/resource/image/upload/product/2022/11/202211021105388aee0e06-df0b-4ffe-ab0e-29e7924913ff.jpg/melon/resize/90x125/strip/true\" alt=\"\">\n                                        <span class=\"frame\"></span>\n                                    </a>\n                                </div>\n                                <p class=\"infor_text\">\n                                    <span class=\"ico_wrap\">\n                                        <span class=\"ico_list ico_list4\"> 판매중</span></span>\n                                    <span class=\"show_title\"><a href=\"/performance/index.htm?prodId=207492\">WATSON，THE MAESTRO－알버트 왓슨 사진전</a></span>\n                                </p>\n                            </div>\n                        </td>\n                        <td class=\"show_date\"><!-- @@@ 2016.02.01 class명 추가 -->\n                            2022.12.08 - 2023.03.30</td>\n                        <td class=\"show_loc\">예술의전당 한가람미술관 2층</td><!-- @@@ 2016.02.01 class명 추가 -->","link":"https://ticket.melon.com/performance/index.htm?prodId=207492","retrieved":1675595436922,"image":"https://cdnticket.melon.co.kr/resource/image/upload/product/2022/11/202211021105388aee0e06-df0b-4ffe-ab0e-29e7924913ff.jpg/melon/resize/90x125/strip/true"},{"title":"미키 마우스 나우 앤 퓨처 Mickey Mouse Now and Future","contents":"<td>\n                            <div class=\"show_infor\">\n                                <div class=\"thumb_90x125  img\">\n                                    <a href=\"#\">\n                                        <img onerror=\"noImage(this, 90, 125)\" src=\"https://cdnticket.melon.co.kr/resource/image/upload/product/2022/12/2022120916382983cd31da-fa90-4114-b04a-18bf59feb6c1.jpg/melon/resize/90x125/strip/true\" alt=\"\">\n                                        <span class=\"frame\"></span>\n                                    </a>\n                                </div>\n                                <p class=\"infor_text\">\n                                    <span class=\"ico_wrap\">\n                                        <span class=\"ico_list ico_list4\"> 판매중</span></span>\n                                    <span class=\"show_title\"><a href=\"/performance/index.htm?prodId=207683\">미키 마우스 나우 앤 퓨처 Mickey Mouse Now and Future</a></span>\n                                </p>\n                            </div>\n                        </td>\n                        <td class=\"show_date\"><!-- @@@ 2016.02.01 class명 추가 -->\n                            2022.12.10 - 2023.04.09</td>\n                        <td class=\"show_loc\">예술의전당 한가람미술관 1층</td><!-- @@@ 2016.02.01 class명 추가 -->","link":"https://ticket.melon.com/performance/index.htm?prodId=207683","retrieved":1675595436924,"image":"https://cdnticket.melon.co.kr/resource/image/upload/product/2022/12/2022120916382983cd31da-fa90-4114-b04a-18bf59feb6c1.jpg/melon/resize/90x125/strip/true"},{"title":"THE BOYZ 공식 팬클럽 〈THE B〉 5기 추가 모집","contents":"<td>\n                            <div class=\"show_infor\">\n                                <div class=\"thumb_90x125  img\">\n                                    <a href=\"#\">\n                                        <img onerror=\"noImage(this, 90, 125)\" src=\"https://cdnticket.melon.co.kr/resource/image/upload/product/2022/12/2022121917335434ecbd01-e965-4546-aaad-1d9d7a91bc7d.jpg/melon/resize/90x125/strip/true\" alt=\"\">\n                                        <span class=\"frame\"></span>\n                                    </a>\n                                </div>\n                                <p class=\"infor_text\">\n                                    <span class=\"ico_wrap\">\n                                        <span class=\"ico_list ico_list1\">단독판매</span><span class=\"ico_list ico_list4\"> 판매중</span></span>\n                                    <span class=\"show_title\"><a href=\"/performance/index.htm?prodId=207699\">THE BOYZ 공식 팬클럽 〈THE B〉 5기 추가 모집</a></span>\n                                </p>\n                            </div>\n                        </td>\n                        <td class=\"show_date\"><!-- @@@ 2016.02.01 class명 추가 -->\n                            2022.12.21 - 2023.02.08</td>\n                        <td class=\"show_loc\">- </td><!-- @@@ 2016.02.01 class명 추가 -->","link":"https://ticket.melon.com/performance/index.htm?prodId=207699","retrieved":1675595436927,"image":"https://cdnticket.melon.co.kr/resource/image/upload/product/2022/12/2022121917335434ecbd01-e965-4546-aaad-1d9d7a91bc7d.jpg/melon/resize/90x125/strip/true"},{"title":"뮤지컬 〈베토벤；Beethoven Secret〉","contents":"<td>\n                            <div class=\"show_infor\">\n                                <div class=\"thumb_90x125  img\">\n                                    <a href=\"#\">\n                                        <img onerror=\"noImage(this, 90, 125)\" src=\"https://cdnticket.melon.co.kr/resource/image/upload/product/2022/11/20221116185911679bebce-0b5b-4a0a-bf2e-c0164f8991b0.jpg/melon/resize/90x125/strip/true\" alt=\"\">\n                                        <span class=\"frame\"></span>\n                                    </a>\n                                </div>\n                                <p class=\"infor_text\">\n                                    <span class=\"ico_wrap\">\n                                        <span class=\"ico_list ico_list1\">좌석우위</span><span class=\"ico_list ico_list4\"> 판매중</span></span>\n                                    <span class=\"show_title\"><a href=\"/performance/index.htm?prodId=207516\">뮤지컬 〈베토벤；Beethoven Secret〉</a></span>\n                                </p>\n                            </div>\n                        </td>\n                        <td class=\"show_date\"><!-- @@@ 2016.02.01 class명 추가 -->\n                            2023.01.12 - 2023.03.26</td>\n                        <td class=\"show_loc\">예술의전당 오페라극장</td><!-- @@@ 2016.02.01 class명 추가 -->","link":"https://ticket.melon.com/performance/index.htm?prodId=207516","retrieved":1675595436929,"image":"https://cdnticket.melon.co.kr/resource/image/upload/product/2022/11/20221116185911679bebce-0b5b-4a0a-bf2e-c0164f8991b0.jpg/melon/resize/90x125/strip/true"},{"title":"뮤지컬 알쏭달쏭 캐치！티니핑 〈신비한 상자를 열어라！〉","contents":"<td>\n                            <div class=\"show_infor\">\n                                <div class=\"thumb_90x125  img\">\n                                    <a href=\"#\">\n                                        <img onerror=\"noImage(this, 90, 125)\" src=\"https://cdnticket.melon.co.kr/resource/image/upload/product/2022/12/202212081417073ee7388a-5284-4c94-be4d-a583444033c1.jpg/melon/resize/90x125/strip/true\" alt=\"\">\n                                        <span class=\"frame\"></span>\n                                    </a>\n                                </div>\n                                <p class=\"infor_text\">\n                                    <span class=\"ico_wrap\">\n                                        <span class=\"ico_list ico_list4\"> 판매중</span></span>\n                                    <span class=\"show_title\"><a href=\"/performance/index.htm?prodId=207673\">뮤지컬 알쏭달쏭 캐치！티니핑 〈신비한 상자를 열어라！〉</a></span>\n                                </p>\n                            </div>\n                        </td>\n                        <td class=\"show_date\"><!-- @@@ 2016.02.01 class명 추가 -->\n                            2023.01.21 - 2023.02.26</td>\n                        <td class=\"show_loc\">우리금융아트홀 </td><!-- @@@ 2016.02.01 class명 추가 -->","link":"https://ticket.melon.com/performance/index.htm?prodId=207673","retrieved":1675595436930,"image":"https://cdnticket.melon.co.kr/resource/image/upload/product/2022/12/202212081417073ee7388a-5284-4c94-be4d-a583444033c1.jpg/melon/resize/90x125/strip/true"},{"title":"연극 〈셰익스피어 인 러브〉","contents":"<td>\n                            <div class=\"show_infor\">\n                                <div class=\"thumb_90x125  img\">\n                                    <a href=\"#\">\n                                        <img onerror=\"noImage(this, 90, 125)\" src=\"https://cdnticket.melon.co.kr/resource/image/upload/product/2022/12/20221215102412ac5d5382-18b6-4e25-a7a0-7047057dc3e9.jpg/melon/resize/90x125/strip/true\" alt=\"\">\n                                        <span class=\"frame\"></span>\n                                    </a>\n                                </div>\n                                <p class=\"infor_text\">\n                                    <span class=\"ico_wrap\">\n                                        <span class=\"ico_list ico_list1\">1열보유</span><span class=\"ico_list ico_list4\"> 판매중</span></span>\n                                    <span class=\"show_title\"><a href=\"/performance/index.htm?prodId=207677\">연극 〈셰익스피어 인 러브〉</a></span>\n                                </p>\n                            </div>\n                        </td>\n                        <td class=\"show_date\"><!-- @@@ 2016.02.01 class명 추가 -->\n                            2023.01.28 - 2023.03.26</td>\n                        <td class=\"show_loc\">예술의전당 CJ 토월극장</td><!-- @@@ 2016.02.01 class명 추가 -->","link":"https://ticket.melon.com/performance/index.htm?prodId=207677","retrieved":1675595436933,"image":"https://cdnticket.melon.co.kr/resource/image/upload/product/2022/12/20221215102412ac5d5382-18b6-4e25-a7a0-7047057dc3e9.jpg/melon/resize/90x125/strip/true"},{"title":"먼데이프로젝트 시즌6［WAS SUMMER］지소쿠리클럽 단독 콘서트","contents":"<td>\n                            <div class=\"show_infor\">\n                                <div class=\"thumb_90x125  img\">\n                                    <a href=\"#\">\n                                        <img onerror=\"noImage(this, 90, 125)\" src=\"https://cdnticket.melon.co.kr/resource/image/upload/product/2023/01/20230111170806014faca8-c902-4377-8158-48130de63afc.jpg/melon/resize/90x125/strip/true\" alt=\"\">\n                                        <span class=\"frame\"></span>\n                                    </a>\n                                </div>\n                                <p class=\"infor_text\">\n                                    <span class=\"ico_wrap\">\n                                        <span class=\"ico_list ico_list1\">단독판매</span><span class=\"ico_list ico_list4\"> 판매중</span></span>\n                                    <span class=\"show_title\"><a href=\"/performance/index.htm?prodId=207758\">먼데이프로젝트 시즌6［WAS SUMMER］지소쿠리클럽 단독 콘서트</a></span>\n                                </p>\n                            </div>\n                        </td>\n                        <td class=\"show_date\"><!-- @@@ 2016.02.01 class명 추가 -->\n                            2023.02.06 - 2023.02.06</td>\n                        <td class=\"show_loc\">클럽온에어 </td><!-- @@@ 2016.02.01 class명 추가 -->","link":"https://ticket.melon.com/performance/index.htm?prodId=207758","retrieved":1675595436951,"image":"https://cdnticket.melon.co.kr/resource/image/upload/product/2023/01/20230111170806014faca8-c902-4377-8158-48130de63afc.jpg/melon/resize/90x125/strip/true"},{"title":"IVE 공식 팬클럽 ‘DIVE’ 2기 모집","contents":"<td>\n                            <div class=\"show_infor\">\n                                <div class=\"thumb_90x125  img\">\n                                    <a href=\"#\">\n                                        <img onerror=\"noImage(this, 90, 125)\" src=\"https://cdnticket.melon.co.kr/resource/image/upload/product/2023/02/20230201171537fd8c85d9-b43b-4987-8508-8f8bfe150840.jpg/melon/resize/90x125/strip/true\" alt=\"\">\n                                        <span class=\"frame\"></span>\n                                    </a>\n                                </div>\n                                <p class=\"infor_text\">\n                                    <span class=\"ico_wrap\">\n                                        <span class=\"ico_list ico_list1\">단독판매</span><span class=\"ico_list ico_list4\"> 판매중</span></span>\n                                    <span class=\"show_title\"><a href=\"/performance/index.htm?prodId=207806\">IVE 공식 팬클럽 ‘DIVE’ 2기 모집</a></span>\n                                </p>\n                            </div>\n                        </td>\n                        <td class=\"show_date\"><!-- @@@ 2016.02.01 class명 추가 -->\n                            2023.02.06 - 2023.02.19</td>\n                        <td class=\"show_loc\">- </td><!-- @@@ 2016.02.01 class명 추가 -->","link":"https://ticket.melon.com/performance/index.htm?prodId=207806","retrieved":1675609977199,"image":"https://cdnticket.melon.co.kr/resource/image/upload/product/2023/02/20230201171537fd8c85d9-b43b-4987-8508-8f8bfe150840.jpg/melon/resize/90x125/strip/true"},{"title":"먼데이프로젝트 시즌6［WAS SUMMER］차세대 단독 콘서트","contents":"<td>\n                            <div class=\"show_infor\">\n                                <div class=\"thumb_90x125  img\">\n                                    <a href=\"#\">\n                                        <img onerror=\"noImage(this, 90, 125)\" src=\"https://cdnticket.melon.co.kr/resource/image/upload/product/2023/01/2023011210245058f2bca1-3b77-44b8-a572-8d92261395ef.jpg/melon/resize/90x125/strip/true\" alt=\"\">\n                                        <span class=\"frame\"></span>\n                                    </a>\n                                </div>\n                                <p class=\"infor_text\">\n                                    <span class=\"ico_wrap\">\n                                        <span class=\"ico_list ico_list1\">단독판매</span><span class=\"ico_list ico_list4\"> 판매중</span></span>\n                                    <span class=\"show_title\"><a href=\"/performance/index.htm?prodId=207754\">먼데이프로젝트 시즌6［WAS SUMMER］차세대 단독 콘서트</a></span>\n                                </p>\n                            </div>\n                        </td>\n                        <td class=\"show_date\"><!-- @@@ 2016.02.01 class명 추가 -->\n                            2023.02.07 - 2023.02.07</td>\n                        <td class=\"show_loc\">클럽온에어 </td><!-- @@@ 2016.02.01 class명 추가 -->","link":"https://ticket.melon.com/performance/index.htm?prodId=207754","retrieved":1675609977199,"image":"https://cdnticket.melon.co.kr/resource/image/upload/product/2023/01/2023011210245058f2bca1-3b77-44b8-a572-8d92261395ef.jpg/melon/resize/90x125/strip/true"},{"title":"Tuesday Beach Club 단독 콘서트 ‘WAY’：롤링 28주년 기념 공연","contents":"<td>\n                            <div class=\"show_infor\">\n                                <div class=\"thumb_90x125  img\">\n                                    <a href=\"#\">\n                                        <img onerror=\"noImage(this, 90, 125)\" src=\"https://cdnticket.melon.co.kr/resource/image/upload/product/2022/12/2022122911050184ac9520-ad4b-4e99-a295-0a641fb8ed67.jpg/melon/resize/90x125/strip/true\" alt=\"\">\n                                        <span class=\"frame\"></span>\n                                    </a>\n                                </div>\n                                <p class=\"infor_text\">\n                                    <span class=\"ico_wrap\">\n                                        <span class=\"ico_list ico_list1\">단독판매</span><span class=\"ico_list ico_list4\"> 판매중</span></span>\n                                    <span class=\"show_title\"><a href=\"/performance/index.htm?prodId=207719\">Tuesday Beach Club 단독 콘서트 ‘WAY’：롤링 28주년 기념 공연</a></span>\n                                </p>\n                            </div>\n                        </td>\n                        <td class=\"show_date\"><!-- @@@ 2016.02.01 class명 추가 -->\n                            2023.02.09 - 2023.02.09</td>\n                        <td class=\"show_loc\">롤링홀 </td><!-- @@@ 2016.02.01 class명 추가 -->","link":"https://ticket.melon.com/performance/index.htm?prodId=207719","retrieved":1675609977207,"image":"https://cdnticket.melon.co.kr/resource/image/upload/product/2022/12/2022122911050184ac9520-ad4b-4e99-a295-0a641fb8ed67.jpg/melon/resize/90x125/strip/true"},{"title":"뮤지컬 〈빨래〉","contents":"<td>\n                            <div class=\"show_infor\">\n                                <div class=\"thumb_90x125  img\">\n                                    <a href=\"#\">\n                                        <img onerror=\"noImage(this, 90, 125)\" src=\"https://cdnticket.melon.co.kr/resource/image/upload/product/2023/01/20230118134246aba472b5-93fe-4659-8d91-1d4c198a4da4.jpg/melon/resize/90x125/strip/true\" alt=\"\">\n                                        <span class=\"frame\"></span>\n                                    </a>\n                                </div>\n                                <p class=\"infor_text\">\n                                    <span class=\"ico_wrap\">\n                                        <span class=\"ico_list ico_list4\"> 판매중</span></span>\n                                    <span class=\"show_title\"><a href=\"/performance/index.htm?prodId=207780\">뮤지컬 〈빨래〉</a></span>\n                                </p>\n                            </div>\n                        </td>\n                        <td class=\"show_date\"><!-- @@@ 2016.02.01 class명 추가 -->\n                            2023.02.09 - 2023.10.01</td>\n                        <td class=\"show_loc\">대학로 유니플렉스 2관</td><!-- @@@ 2016.02.01 class명 추가 -->","link":"https://ticket.melon.com/performance/index.htm?prodId=207780","retrieved":1675609977208,"image":"https://cdnticket.melon.co.kr/resource/image/upload/product/2023/01/20230118134246aba472b5-93fe-4659-8d91-1d4c198a4da4.jpg/melon/resize/90x125/strip/true"},{"title":"김마리 단독 콘서트 ‘Fly！’：롤링 28주년 기념 공연","contents":"<td>\n                            <div class=\"show_infor\">\n                                <div class=\"thumb_90x125  img\">\n                                    <a href=\"#\">\n                                        <img onerror=\"noImage(this, 90, 125)\" src=\"https://cdnticket.melon.co.kr/resource/image/upload/product/2022/12/202212291346396011dc66-46af-4cd8-8596-f4fbbf99c1db.jpg/melon/resize/90x125/strip/true\" alt=\"\">\n                                        <span class=\"frame\"></span>\n                                    </a>\n                                </div>\n                                <p class=\"infor_text\">\n                                    <span class=\"ico_wrap\">\n                                        <span class=\"ico_list ico_list1\">단독판매</span><span class=\"ico_list ico_list4\"> 판매중</span></span>\n                                    <span class=\"show_title\"><a href=\"/performance/index.htm?prodId=207720\">김마리 단독 콘서트 ‘Fly！’：롤링 28주년 기념 공연</a></span>\n                                </p>\n                            </div>\n                        </td>\n                        <td class=\"show_date\"><!-- @@@ 2016.02.01 class명 추가 -->\n                            2023.02.10 - 2023.02.10</td>\n                        <td class=\"show_loc\">롤링홀 </td><!-- @@@ 2016.02.01 class명 추가 -->","link":"https://ticket.melon.com/performance/index.htm?prodId=207720","retrieved":1675609977216,"image":"https://cdnticket.melon.co.kr/resource/image/upload/product/2022/12/202212291346396011dc66-46af-4cd8-8596-f4fbbf99c1db.jpg/melon/resize/90x125/strip/true"},{"title":"김가람 피아노 리사이틀 ‘Lament’","contents":"<td>\n                            <div class=\"show_infor\">\n                                <div class=\"thumb_90x125  img\">\n                                    <a href=\"#\">\n                                        <img onerror=\"noImage(this, 90, 125)\" src=\"https://cdnticket.melon.co.kr/resource/image/upload/product/2023/01/20230117164424446ea40a-d454-48f8-a6ee-158695b70d2d.jpg/melon/resize/90x125/strip/true\" alt=\"\">\n                                        <span class=\"frame\"></span>\n                                    </a>\n                                </div>\n                                <p class=\"infor_text\">\n                                    <span class=\"ico_wrap\">\n                                        <span class=\"ico_list ico_list4\"> 판매중</span></span>\n                                    <span class=\"show_title\"><a href=\"/performance/index.htm?prodId=207778\">김가람 피아노 리사이틀 ‘Lament’</a></span>\n                                </p>\n                            </div>\n                        </td>\n                        <td class=\"show_date\"><!-- @@@ 2016.02.01 class명 추가 -->\n                            2023.02.10 - 2023.02.10</td>\n                        <td class=\"show_loc\">세종문화회관 체임버홀</td><!-- @@@ 2016.02.01 class명 추가 -->","link":"https://ticket.melon.com/performance/index.htm?prodId=207778","retrieved":1675609977216,"image":"https://cdnticket.melon.co.kr/resource/image/upload/product/2023/01/20230117164424446ea40a-d454-48f8-a6ee-158695b70d2d.jpg/melon/resize/90x125/strip/true"}]}