{"title":"멜론티켓 ─ 판매중","url":"https://ticket.melon.com/place/ajax/list_album.htm","favicon":"https://ticket.melon.com/place/ajax/favicon.ico","elements":[{"title":"치유의 기술 / Technique of Healing－부산","contents":"<td>\n                            <div class=\"show_infor\">\n                                <div class=\"thumb_90x125  img\">\n                                    <a href=\"#\">\n                                        <img onerror=\"noImage(this, 90, 125)\" src=\"https://cdnticket.melon.co.kr/resource/image/upload/product/2022/03/2022030715241512eef925-8c62-493e-8b87-6087b341f7cd.jpg/melon/resize/90x125/strip/true\" alt=\"\">\n                                        <span class=\"frame\"></span>\n                                    </a>\n                                </div>\n                                <p class=\"infor_text\">\n                                    <span class=\"ico_wrap\">\n                                        <span class=\"ico_list ico_list4\"> 판매중</span></span>\n                                    <span class=\"show_title\"><a href=\"/performance/index.htm?prodId=206655\">치유의 기술 / Technique of Healing－부산</a></span>\n                                </p>\n                            </div>\n                        </td>\n                        <td class=\"show_date\"><!-- @@@ 2016.02.01 class명 추가 -->\n                            2022.03.26 - 2023.05.07</td>\n                        <td class=\"show_loc\">뮤지엄 원 </td><!-- @@@ 2016.02.01 class명 추가 -->","link":"https://ticket.melon.com/performance/index.htm?prodId=206655","retrieved":1677107578480,"image":"https://cdnticket.melon.co.kr/resource/image/upload/product/2022/03/2022030715241512eef925-8c62-493e-8b87-6087b341f7cd.jpg/melon/resize/90x125/strip/true"},{"title":"프랑코 폰타나：컬러 인 라이프","contents":"<td>\n                            <div class=\"show_infor\">\n                                <div class=\"thumb_90x125  img\">\n                                    <a href=\"#\">\n                                        <img onerror=\"noImage(this, 90, 125)\" src=\"https://cdnticket.melon.co.kr/resource/image/upload/product/2022/09/2022092911383419866293-4561-4a1c-919b-adc94918ff8d.jpg/melon/resize/90x125/strip/true\" alt=\"\">\n                                        <span class=\"frame\"></span>\n                                    </a>\n                                </div>\n                                <p class=\"infor_text\">\n                                    <span class=\"ico_wrap\">\n                                        <span class=\"ico_list ico_list4\"> 판매중</span></span>\n                                    <span class=\"show_title\"><a href=\"/performance/index.htm?prodId=207379\">프랑코&nbsp;폰타나：컬러 인 라이프</a></span>\n                                </p>\n                            </div>\n                        </td>\n                        <td class=\"show_date\"><!-- @@@ 2016.02.01 class명 추가 -->\n                            2022.09.30 - 2023.03.01</td>\n                        <td class=\"show_loc\">마이아트뮤지엄 </td><!-- @@@ 2016.02.01 class명 추가 -->","link":"https://ticket.melon.com/performance/index.htm?prodId=207379","retrieved":1677107578483,"image":"https://cdnticket.melon.co.kr/resource/image/upload/product/2022/09/2022092911383419866293-4561-4a1c-919b-adc94918ff8d.jpg/melon/resize/90x125/strip/true"},{"title":"하리보 골드베렌 100주년 생일 기념전","contents":"<td>\n                            <div class=\"show_infor\">\n                                <div class=\"thumb_90x125  img\">\n                                    <a href=\"#\">\n                                        <img onerror=\"noImage(this, 90, 125)\" src=\"https://cdnticket.melon.co.kr/resource/image/upload/product/2022/10/202210121324282ba41fd7-0b2a-41e1-9f66-d12674c1bbf8.jpg/melon/resize/90x125/strip/true\" alt=\"\">\n                                        <span class=\"frame\"></span>\n                                    </a>\n                                </div>\n                                <p class=\"infor_text\">\n                                    <span class=\"ico_wrap\">\n                                        <span class=\"ico_list ico_list4\"> 판매중</span></span>\n                                    <span class=\"show_title\"><a href=\"/performance/index.htm?prodId=207416\">하리보 골드베렌 100주년 생일 기념전</a></span>\n                                </p>\n                            </div>\n                        </td>\n                        <td class=\"show_date\"><!-- @@@ 2016.02.01 class명 추가 -->\n                            2022.10.13 - 2023.03.12</td>\n                        <td class=\"show_loc\">안녕 인사동 B1 인사센트럴뮤지엄 </td><!-- @@@ 2016.02.01 class명 추가 -->","link":"https://ticket.melon.com/performance/index.htm?prodId=207416","retrieved":1677107578485,"image":"https://cdnticket.melon.co.kr/resource/image/upload/product/2022/10/202210121324282ba41fd7-0b2a-41e1-9f66-d12674c1bbf8.jpg/melon/resize/90x125/strip/true"},{"title":"뮤지컬 〈웨스트 사이드 스토리〉","contents":"<td>\n                            <div class=\"show_infor\">\n                                <div class=\"thumb_90x125  img\">\n                                    <a href=\"#\">\n                                        <img onerror=\"noImage(this, 90, 125)\" src=\"https://cdnticket.melon.co.kr/resource/image/upload/product/2022/09/202209071858267b4b3416-0656-4711-b7c2-956ff6449d64.jpg/melon/resize/90x125/strip/true\" alt=\"\">\n                                        <span class=\"frame\"></span>\n                                    </a>\n                                </div>\n                                <p class=\"infor_text\">\n                                    <span class=\"ico_wrap\">\n                                        <span class=\"ico_list ico_list1\">1열보유</span><span class=\"ico_list ico_list4\"> 판매중</span></span>\n                                    <span class=\"show_title\"><a href=\"/performance/index.htm?prodId=207296\">뮤지컬 〈웨스트 사이드 스토리〉</a></span>\n                                </p>\n                            </div>\n                        </td>\n                        <td class=\"show_date\"><!-- @@@ 2016.02.01 class명 추가 -->\n                            2022.11.17 - 2023.02.26</td>\n                        <td class=\"show_loc\">충무아트센터 대극장</td><!-- @@@ 2016.02.01 class명 추가 -->","link":"https://ticket.melon.com/performance/index.htm?prodId=207296","retrieved":1677107578486,"image":"https://cdnticket.melon.co.kr/resource/image/upload/product/2022/09/202209071858267b4b3416-0656-4711-b7c2-956ff6449d64.jpg/melon/resize/90x125/strip/true"},{"title":"헬가스텐첼 사진전","contents":"<td>\n                            <div class=\"show_infor\">\n                                <div class=\"thumb_90x125  img\">\n                                    <a href=\"#\">\n                                        <img onerror=\"noImage(this, 90, 125)\" src=\"https://cdnticket.melon.co.kr/resource/image/upload/product/2022/11/202211171608490eba859d-1b55-4c4f-99f6-241cadaaec0c.jpg/melon/resize/90x125/strip/true\" alt=\"\">\n                                        <span class=\"frame\"></span>\n                                    </a>\n                                </div>\n                                <p class=\"infor_text\">\n                                    <span class=\"ico_wrap\">\n                                        <span class=\"ico_list ico_list4\"> 판매중</span></span>\n                                    <span class=\"show_title\"><a href=\"/performance/index.htm?prodId=207583\">헬가스텐첼 사진전</a></span>\n                                </p>\n                            </div>\n                        </td>\n                        <td class=\"show_date\"><!-- @@@ 2016.02.01 class명 추가 -->\n                            2022.11.18 - 2023.03.01</td>\n                        <td class=\"show_loc\">롯데컬쳐스퀘어 CxC Art Museum </td><!-- @@@ 2016.02.01 class명 추가 -->","link":"https://ticket.melon.com/performance/index.htm?prodId=207583","retrieved":1677107578487,"image":"https://cdnticket.melon.co.kr/resource/image/upload/product/2022/11/202211171608490eba859d-1b55-4c4f-99f6-241cadaaec0c.jpg/melon/resize/90x125/strip/true"},{"title":"뮤지컬 〈이프덴〉","contents":"<td>\n                            <div class=\"show_infor\">\n                                <div class=\"thumb_90x125  img\">\n                                    <a href=\"#\">\n                                        <img onerror=\"noImage(this, 90, 125)\" src=\"https://cdnticket.melon.co.kr/resource/image/upload/product/2022/10/2022101210464406c2f97c-f12d-4632-8c75-7b84502afa7b.jpg/melon/resize/90x125/strip/true\" alt=\"\">\n                                        <span class=\"frame\"></span>\n                                    </a>\n                                </div>\n                                <p class=\"infor_text\">\n                                    <span class=\"ico_wrap\">\n                                        <span class=\"ico_list ico_list1\">1열보유</span><span class=\"ico_list ico_list4\"> 판매중</span></span>\n                                    <span class=\"show_title\"><a href=\"/performance/index.htm?prodId=207399\">뮤지컬 〈이프덴〉</a></span>\n                                </p>\n                            </div>\n                        </td>\n                        <td class=\"show_date\"><!-- @@@ 2016.02.01 class명 추가 -->\n                            2022.12.08 - 2023.02.26</td>\n                        <td class=\"show_loc\">홍익대학교 대학로 아트센터 대극장</td><!-- @@@ 2016.02.01 class명 추가 -->","link":"https://ticket.melon.com/performance/index.htm?prodId=207399","retrieved":1677107578490,"image":"https://cdnticket.melon.co.kr/resource/image/upload/product/2022/10/2022101210464406c2f97c-f12d-4632-8c75-7b84502afa7b.jpg/melon/resize/90x125/strip/true"},{"title":"DRIFT：In Sync with the Earth","contents":"<td>\n                            <div class=\"show_infor\">\n                                <div class=\"thumb_90x125  img\">\n                                    <a href=\"#\">\n                                        <img onerror=\"noImage(this, 90, 125)\" src=\"https://cdnticket.melon.co.kr/resource/image/upload/product/2022/12/202212061105295f572422-94ee-49c0-b916-142eb8aefbbb.jpg/melon/resize/90x125/strip/true\" alt=\"\">\n                                        <span class=\"frame\"></span>\n                                    </a>\n                                </div>\n                                <p class=\"infor_text\">\n                                    <span class=\"ico_wrap\">\n                                        <span class=\"ico_list ico_list4\"> 판매중</span></span>\n                                    <span class=\"show_title\"><a href=\"/performance/index.htm?prodId=207665\">DRIFT：In Sync with the Earth</a></span>\n                                </p>\n                            </div>\n                        </td>\n                        <td class=\"show_date\"><!-- @@@ 2016.02.01 class명 추가 -->\n                            2022.12.08 - 2023.04.16</td>\n                        <td class=\"show_loc\">현대카드 스토리지 </td><!-- @@@ 2016.02.01 class명 추가 -->","link":"https://ticket.melon.com/performance/index.htm?prodId=207665","retrieved":1677107578507,"image":"https://cdnticket.melon.co.kr/resource/image/upload/product/2022/12/202212061105295f572422-94ee-49c0-b916-142eb8aefbbb.jpg/melon/resize/90x125/strip/true"},{"title":"WATSON，THE MAESTRO－알버트 왓슨 사진전","contents":"<td>\n                            <div class=\"show_infor\">\n                                <div class=\"thumb_90x125  img\">\n                                    <a href=\"#\">\n                                        <img onerror=\"noImage(this, 90, 125)\" src=\"https://cdnticket.melon.co.kr/resource/image/upload/product/2022/11/202211021105388aee0e06-df0b-4ffe-ab0e-29e7924913ff.jpg/melon/resize/90x125/strip/true\" alt=\"\">\n                                        <span class=\"frame\"></span>\n                                    </a>\n                                </div>\n                                <p class=\"infor_text\">\n                                    <span class=\"ico_wrap\">\n                                        <span class=\"ico_list ico_list4\"> 판매중</span></span>\n                                    <span class=\"show_title\"><a href=\"/performance/index.htm?prodId=207492\">WATSON，THE MAESTRO－알버트 왓슨 사진전</a></span>\n                                </p>\n                            </div>\n                        </td>\n                        <td class=\"show_date\"><!-- @@@ 2016.02.01 class명 추가 -->\n                            2022.12.08 - 2023.03.30</td>\n                        <td class=\"show_loc\">예술의전당 한가람미술관 2층</td><!-- @@@ 2016.02.01 class명 추가 -->","link":"https://ticket.melon.com/performance/index.htm?prodId=207492","retrieved":1677107578508,"image":"https://cdnticket.melon.co.kr/resource/image/upload/product/2022/11/202211021105388aee0e06-df0b-4ffe-ab0e-29e7924913ff.jpg/melon/resize/90x125/strip/true"},{"title":"미키 마우스 나우 앤 퓨처 Mickey Mouse Now and Future","contents":"<td>\n                            <div class=\"show_infor\">\n                                <div class=\"thumb_90x125  img\">\n                                    <a href=\"#\">\n                                        <img onerror=\"noImage(this, 90, 125)\" src=\"https://cdnticket.melon.co.kr/resource/image/upload/product/2022/12/2022120916382983cd31da-fa90-4114-b04a-18bf59feb6c1.jpg/melon/resize/90x125/strip/true\" alt=\"\">\n                                        <span class=\"frame\"></span>\n                                    </a>\n                                </div>\n                                <p class=\"infor_text\">\n                                    <span class=\"ico_wrap\">\n                                        <span class=\"ico_list ico_list4\"> 판매중</span></span>\n                                    <span class=\"show_title\"><a href=\"/performance/index.htm?prodId=207683\">미키 마우스 나우 앤 퓨처 Mickey Mouse Now and Future</a></span>\n                                </p>\n                            </div>\n                        </td>\n                        <td class=\"show_date\"><!-- @@@ 2016.02.01 class명 추가 -->\n                            2022.12.10 - 2023.04.09</td>\n                        <td class=\"show_loc\">예술의전당 한가람미술관 1층</td><!-- @@@ 2016.02.01 class명 추가 -->","link":"https://ticket.melon.com/performance/index.htm?prodId=207683","retrieved":1677107578520,"image":"https://cdnticket.melon.co.kr/resource/image/upload/product/2022/12/2022120916382983cd31da-fa90-4114-b04a-18bf59feb6c1.jpg/melon/resize/90x125/strip/true"},{"title":"뮤지컬 〈베토벤；Beethoven Secret〉","contents":"<td>\n                            <div class=\"show_infor\">\n                                <div class=\"thumb_90x125  img\">\n                                    <a href=\"#\">\n                                        <img onerror=\"noImage(this, 90, 125)\" src=\"https://cdnticket.melon.co.kr/resource/image/upload/product/2022/11/20221116185911679bebce-0b5b-4a0a-bf2e-c0164f8991b0.jpg/melon/resize/90x125/strip/true\" alt=\"\">\n                                        <span class=\"frame\"></span>\n                                    </a>\n                                </div>\n                                <p class=\"infor_text\">\n                                    <span class=\"ico_wrap\">\n                                        <span class=\"ico_list ico_list1\">좌석우위</span><span class=\"ico_list ico_list4\"> 판매중</span></span>\n                                    <span class=\"show_title\"><a href=\"/performance/index.htm?prodId=207516\">뮤지컬 〈베토벤；Beethoven Secret〉</a></span>\n                                </p>\n                            </div>\n                        </td>\n                        <td class=\"show_date\"><!-- @@@ 2016.02.01 class명 추가 -->\n                            2023.01.12 - 2023.03.26</td>\n                        <td class=\"show_loc\">예술의전당 오페라극장</td><!-- @@@ 2016.02.01 class명 추가 -->","link":"https://ticket.melon.com/performance/index.htm?prodId=207516","retrieved":1677107578520,"image":"https://cdnticket.melon.co.kr/resource/image/upload/product/2022/11/20221116185911679bebce-0b5b-4a0a-bf2e-c0164f8991b0.jpg/melon/resize/90x125/strip/true"},{"title":"뮤지컬 알쏭달쏭 캐치！티니핑 〈신비한 상자를 열어라！〉","contents":"<td>\n                            <div class=\"show_infor\">\n                                <div class=\"thumb_90x125  img\">\n                                    <a href=\"#\">\n                                        <img onerror=\"noImage(this, 90, 125)\" src=\"https://cdnticket.melon.co.kr/resource/image/upload/product/2022/12/202212081417073ee7388a-5284-4c94-be4d-a583444033c1.jpg/melon/resize/90x125/strip/true\" alt=\"\">\n                                        <span class=\"frame\"></span>\n                                    </a>\n                                </div>\n                                <p class=\"infor_text\">\n                                    <span class=\"ico_wrap\">\n                                        <span class=\"ico_list ico_list4\"> 판매중</span></span>\n                                    <span class=\"show_title\"><a href=\"/performance/index.htm?prodId=207673\">뮤지컬 알쏭달쏭 캐치！티니핑 〈신비한 상자를 열어라！〉</a></span>\n                                </p>\n                            </div>\n                        </td>\n                        <td class=\"show_date\"><!-- @@@ 2016.02.01 class명 추가 -->\n                            2023.01.21 - 2023.02.26</td>\n                        <td class=\"show_loc\">우리금융아트홀 </td><!-- @@@ 2016.02.01 class명 추가 -->","link":"https://ticket.melon.com/performance/index.htm?prodId=207673","retrieved":1677107578520,"image":"https://cdnticket.melon.co.kr/resource/image/upload/product/2022/12/202212081417073ee7388a-5284-4c94-be4d-a583444033c1.jpg/melon/resize/90x125/strip/true"},{"title":"연극 〈셰익스피어 인 러브〉","contents":"<td>\n                            <div class=\"show_infor\">\n                                <div class=\"thumb_90x125  img\">\n                                    <a href=\"#\">\n                                        <img onerror=\"noImage(this, 90, 125)\" src=\"https://cdnticket.melon.co.kr/resource/image/upload/product/2022/12/20221215102412ac5d5382-18b6-4e25-a7a0-7047057dc3e9.jpg/melon/resize/90x125/strip/true\" alt=\"\">\n                                        <span class=\"frame\"></span>\n                                    </a>\n                                </div>\n                                <p class=\"infor_text\">\n                                    <span class=\"ico_wrap\">\n                                        <span class=\"ico_list ico_list1\">1열보유</span><span class=\"ico_list ico_list4\"> 판매중</span></span>\n                                    <span class=\"show_title\"><a href=\"/performance/index.htm?prodId=207677\">연극 〈셰익스피어 인 러브〉</a></span>\n                                </p>\n                            </div>\n                        </td>\n                        <td class=\"show_date\"><!-- @@@ 2016.02.01 class명 추가 -->\n                            2023.01.28 - 2023.03.26</td>\n                        <td class=\"show_loc\">예술의전당 CJ 토월극장</td><!-- @@@ 2016.02.01 class명 추가 -->","link":"https://ticket.melon.com/performance/index.htm?prodId=207677","retrieved":1677107578520,"image":"https://cdnticket.melon.co.kr/resource/image/upload/product/2022/12/20221215102412ac5d5382-18b6-4e25-a7a0-7047057dc3e9.jpg/melon/resize/90x125/strip/true"},{"title":"뮤지컬 〈빨래〉","contents":"<td>\n                            <div class=\"show_infor\">\n                                <div class=\"thumb_90x125  img\">\n                                    <a href=\"#\">\n                                        <img onerror=\"noImage(this, 90, 125)\" src=\"https://cdnticket.melon.co.kr/resource/image/upload/product/2023/01/20230118134246aba472b5-93fe-4659-8d91-1d4c198a4da4.jpg/melon/resize/90x125/strip/true\" alt=\"\">\n                                        <span class=\"frame\"></span>\n                                    </a>\n                                </div>\n                                <p class=\"infor_text\">\n                                    <span class=\"ico_wrap\">\n                                        <span class=\"ico_list ico_list4\"> 판매중</span></span>\n                                    <span class=\"show_title\"><a href=\"/performance/index.htm?prodId=207780\">뮤지컬 〈빨래〉</a></span>\n                                </p>\n                            </div>\n                        </td>\n                        <td class=\"show_date\"><!-- @@@ 2016.02.01 class명 추가 -->\n                            2023.02.09 - 2023.10.01</td>\n                        <td class=\"show_loc\">대학로 유니플렉스 2관</td><!-- @@@ 2016.02.01 class명 추가 -->","link":"https://ticket.melon.com/performance/index.htm?prodId=207780","retrieved":1677107578521,"image":"https://cdnticket.melon.co.kr/resource/image/upload/product/2023/01/20230118134246aba472b5-93fe-4659-8d91-1d4c198a4da4.jpg/melon/resize/90x125/strip/true"},{"title":"아이유 공식 팬클럽 〈유애나〉 6기 모집","contents":"<td>\n                            <div class=\"show_infor\">\n                                <div class=\"thumb_90x125  img\">\n                                    <a href=\"#\">\n                                        <img onerror=\"noImage(this, 90, 125)\" src=\"https://cdnticket.melon.co.kr/resource/image/upload/product/2023/02/20230213090550f64319cc-0046-4ad3-9019-e217e3754f9f.jpg/melon/resize/90x125/strip/true\" alt=\"\">\n                                        <span class=\"frame\"></span>\n                                    </a>\n                                </div>\n                                <p class=\"infor_text\">\n                                    <span class=\"ico_wrap\">\n                                        <span class=\"ico_list ico_list1\">단독판매</span><span class=\"ico_list ico_list4\"> 판매중</span></span>\n                                    <span class=\"show_title\"><a href=\"/performance/index.htm?prodId=207816\">아이유 공식 팬클럽 〈유애나〉 6기 모집</a></span>\n                                </p>\n                            </div>\n                        </td>\n                        <td class=\"show_date\"><!-- @@@ 2016.02.01 class명 추가 -->\n                            2023.02.13 - 2023.02.26</td>\n                        <td class=\"show_loc\">- </td><!-- @@@ 2016.02.01 class명 추가 -->","link":"https://ticket.melon.com/performance/index.htm?prodId=207816","retrieved":1677107578521,"image":"https://cdnticket.melon.co.kr/resource/image/upload/product/2023/02/20230213090550f64319cc-0046-4ad3-9019-e217e3754f9f.jpg/melon/resize/90x125/strip/true"},{"title":"안예은 단독 콘서트 ‘쉽게 듣는 노래들’：롤링 28주년 기념 공연","contents":"<td>\n                            <div class=\"show_infor\">\n                                <div class=\"thumb_90x125  img\">\n                                    <a href=\"#\">\n                                        <img onerror=\"noImage(this, 90, 125)\" src=\"https://cdnticket.melon.co.kr/resource/image/upload/product/2023/01/2023013014451546569b14-a141-46f1-9b20-d8667b9b1755.jpg/melon/resize/90x125/strip/true\" alt=\"\">\n                                        <span class=\"frame\"></span>\n                                    </a>\n                                </div>\n                                <p class=\"infor_text\">\n                                    <span class=\"ico_wrap\">\n                                        <span class=\"ico_list ico_list1\">단독판매</span><span class=\"ico_list ico_list4\"> 판매중</span></span>\n                                    <span class=\"show_title\"><a href=\"/performance/index.htm?prodId=207800\">안예은 단독 콘서트 ‘쉽게 듣는 노래들’：롤링 28주년 기념 공연</a></span>\n                                </p>\n                            </div>\n                        </td>\n                        <td class=\"show_date\"><!-- @@@ 2016.02.01 class명 추가 -->\n                            2023.02.24 - 2023.02.24</td>\n                        <td class=\"show_loc\">롤링홀 </td><!-- @@@ 2016.02.01 class명 추가 -->","link":"https://ticket.melon.com/performance/index.htm?prodId=207800","retrieved":1677107578524,"image":"https://cdnticket.melon.co.kr/resource/image/upload/product/2023/01/2023013014451546569b14-a141-46f1-9b20-d8667b9b1755.jpg/melon/resize/90x125/strip/true"},{"title":"김현철 단독 공연 “김현철 도시의밤”","contents":"<td>\n                            <div class=\"show_infor\">\n                                <div class=\"thumb_90x125  img\">\n                                    <a href=\"#\">\n                                        <img onerror=\"noImage(this, 90, 125)\" src=\"https://cdnticket.melon.co.kr/resource/image/upload/product/2023/02/202302021445178d4ad6d1-11e1-4033-9190-9c341ce61cd9.jpg/melon/resize/90x125/strip/true\" alt=\"\">\n                                        <span class=\"frame\"></span>\n                                    </a>\n                                </div>\n                                <p class=\"infor_text\">\n                                    <span class=\"ico_wrap\">\n                                        <span class=\"ico_list ico_list1\">단독판매</span><span class=\"ico_list ico_list4\"> 판매중</span></span>\n                                    <span class=\"show_title\"><a href=\"/performance/index.htm?prodId=207809\">김현철 단독 공연 “김현철 도시의밤”</a></span>\n                                </p>\n                            </div>\n                        </td>\n                        <td class=\"show_date\"><!-- @@@ 2016.02.01 class명 추가 -->\n                            2023.02.24 - 2023.02.24</td>\n                        <td class=\"show_loc\">클럽온에어 </td><!-- @@@ 2016.02.01 class명 추가 -->","link":"https://ticket.melon.com/performance/index.htm?prodId=207809","retrieved":1677107578526,"image":"https://cdnticket.melon.co.kr/resource/image/upload/product/2023/02/202302021445178d4ad6d1-11e1-4033-9190-9c341ce61cd9.jpg/melon/resize/90x125/strip/true"},{"title":"제 58회 라이브 클럽 데이 with 멜론 트랙제로－블라인드 티켓","contents":"<td>\n                            <div class=\"show_infor\">\n                                <div class=\"thumb_90x125  img\">\n                                    <a href=\"#\">\n                                        <img onerror=\"noImage(this, 90, 125)\" src=\"https://cdnticket.melon.co.kr/resource/image/upload/product/2023/02/2023020617541318d43005-c147-40a4-8c24-100b4ebba699.jpg/melon/resize/90x125/strip/true\" alt=\"\">\n                                        <span class=\"frame\"></span>\n                                    </a>\n                                </div>\n                                <p class=\"infor_text\">\n                                    <span class=\"ico_wrap\">\n                                        <span class=\"ico_list ico_list1\">단독판매</span><span class=\"ico_list ico_list4\"> 판매중</span></span>\n                                    <span class=\"show_title\"><a href=\"/performance/index.htm?prodId=207820\">제 58회 라이브 클럽 데이 with 멜론 트랙제로－블라인드 티켓</a></span>\n                                </p>\n                            </div>\n                        </td>\n                        <td class=\"show_date\"><!-- @@@ 2016.02.01 class명 추가 -->\n                            2023.02.24 - 2023.02.24</td>\n                        <td class=\"show_loc\">LIVE CLUB DAY </td><!-- @@@ 2016.02.01 class명 추가 -->","link":"https://ticket.melon.com/performance/index.htm?prodId=207820","retrieved":1677107578526,"image":"https://cdnticket.melon.co.kr/resource/image/upload/product/2023/02/2023020617541318d43005-c147-40a4-8c24-100b4ebba699.jpg/melon/resize/90x125/strip/true"},{"title":"제 58회 라이브 클럽 데이 with 멜론 트랙제로","contents":"<td>\n                            <div class=\"show_infor\">\n                                <div class=\"thumb_90x125  img\">\n                                    <a href=\"#\">\n                                        <img onerror=\"noImage(this, 90, 125)\" src=\"https://cdnticket.melon.co.kr/resource/image/upload/product/2023/02/202302101352256202ac9d-ffe4-48f2-84d8-c83dc0a284f5.jpg/melon/resize/90x125/strip/true\" alt=\"\">\n                                        <span class=\"frame\"></span>\n                                    </a>\n                                </div>\n                                <p class=\"infor_text\">\n                                    <span class=\"ico_wrap\">\n                                        <span class=\"ico_list ico_list4\"> 판매중</span></span>\n                                    <span class=\"show_title\"><a href=\"/performance/index.htm?prodId=207852\">제 58회 라이브 클럽 데이 with 멜론 트랙제로</a></span>\n                                </p>\n                            </div>\n                        </td>\n                        <td class=\"show_date\"><!-- @@@ 2016.02.01 class명 추가 -->\n                            2023.02.24 - 2023.02.24</td>\n                        <td class=\"show_loc\">LIVE CLUB DAY </td><!-- @@@ 2016.02.01 class명 추가 -->","link":"https://ticket.melon.com/performance/index.htm?prodId=207852","retrieved":1677165399573,"image":"https://cdnticket.melon.co.kr/resource/image/upload/product/2023/02/202302101352256202ac9d-ffe4-48f2-84d8-c83dc0a284f5.jpg/melon/resize/90x125/strip/true"},{"title":"김현철 단독 공연 “김현철 도시의밤” 애프터 파티","contents":"<td>\n                            <div class=\"show_infor\">\n                                <div class=\"thumb_90x125  img\">\n                                    <a href=\"#\">\n                                        <img onerror=\"noImage(this, 90, 125)\" src=\"https://cdnticket.melon.co.kr/resource/image/upload/product/2023/02/20230217111525a066285b-11c6-4501-a758-f815c8b277d3.jpg/melon/resize/90x125/strip/true\" alt=\"\">\n                                        <span class=\"frame\"></span>\n                                    </a>\n                                </div>\n                                <p class=\"infor_text\">\n                                    <span class=\"ico_wrap\">\n                                        <span class=\"ico_list ico_list1\">단독판매</span><span class=\"ico_list ico_list4\"> 판매중</span></span>\n                                    <span class=\"show_title\"><a href=\"/performance/index.htm?prodId=207877\">김현철 단독 공연 “김현철 도시의밤” 애프터 파티</a></span>\n                                </p>\n                            </div>\n                        </td>\n                        <td class=\"show_date\"><!-- @@@ 2016.02.01 class명 추가 -->\n                            2023.02.24 - 2023.02.24</td>\n                        <td class=\"show_loc\">클럽온에어 </td><!-- @@@ 2016.02.01 class명 추가 -->","link":"https://ticket.melon.com/performance/index.htm?prodId=207877","retrieved":1677165399573,"image":"https://cdnticket.melon.co.kr/resource/image/upload/product/2023/02/20230217111525a066285b-11c6-4501-a758-f815c8b277d3.jpg/melon/resize/90x125/strip/true"},{"title":"이솔로몬 첫 번째 단독 콘서트 〈손으로 써 내려간 것들〉－부산","contents":"<td>\n                            <div class=\"show_infor\">\n                                <div class=\"thumb_90x125  img\">\n                                    <a href=\"#\">\n                                        <img onerror=\"noImage(this, 90, 125)\" src=\"https://cdnticket.melon.co.kr/resource/image/upload/product/2023/01/202301101119239fe62e56-40f2-44e5-8780-3bf9e8e731ec.jpg/melon/resize/90x125/strip/true\" alt=\"\">\n                                        <span class=\"frame\"></span>\n                                    </a>\n                                </div>\n                                <p class=\"infor_text\">\n                                    <span class=\"ico_wrap\">\n                                        <span class=\"ico_list ico_list4\"> 판매중</span></span>\n                                    <span class=\"show_title\"><a href=\"/performance/index.htm?prodId=207738\">이솔로몬 첫 번째 단독 콘서트 〈손으로 써 내려간 것들〉－부산</a></span>\n                                </p>\n                            </div>\n                        </td>\n                        <td class=\"show_date\"><!-- @@@ 2016.02.01 class명 추가 -->\n                            2023.02.25 - 2023.02.26</td>\n                        <td class=\"show_loc\">소향씨어터 신한카드홀 </td><!-- @@@ 2016.02.01 class명 추가 -->","link":"https://ticket.melon.com/performance/index.htm?prodId=207738","retrieved":1677165399574,"image":"https://cdnticket.melon.co.kr/resource/image/upload/product/2023/01/202301101119239fe62e56-40f2-44e5-8780-3bf9e8e731ec.jpg/melon/resize/90x125/strip/true"}]}